mapf_branch_and_bound/__init__.py
mapf_branch_and_bound/assignment_problem.py
mapf_branch_and_bound/assignment_solver.py
mapf_branch_and_bound/bbnode.py
mapf_branch_and_bound/bbsolver.py
mapf_branch_and_bound-0.0.3.dist-info/LICENSE
mapf_branch_and_bound-0.0.3.dist-info/METADATA
mapf_branch_and_bound-0.0.3.dist-info/WHEEL
mapf_branch_and_bound-0.0.3.dist-info/top_level.txt
mapf_branch_and_bound-0.0.3.dist-info/RECORD
