Metadata-Version: 2.1
Name: mapf-branch-and-bound
Version: 0.0.3
Summary: A branch-and-bound framework for MAPF solvers that use mapfmclient
Home-page: https://github.com/tbvanderwoude/mapf-branch-and-bound/
Author: Thom van der Woude
Author-email: tbvanderwoude@student.tudelft.nl
License: UNKNOWN
Project-URL: Bug Tracker, https://github.com/tbvanderwoude/mapf-branch-and-bozund/issues
Platform: UNKNOWN
Classifier: Programming Language :: Python :: 3
Classifier: License :: OSI Approved :: MIT License
Classifier: Operating System :: OS Independent
Requires-Python: >=3.9
License-File: LICENSE
